Metadata-Version: 2.4
Name: desktop_env
Version: 1.0.2
Summary: The package provides a desktop environment for setting and evaluating desktop automation tasks.
Home-page: https://github.com/xlang-ai/desktop_env
Author: Tianbao Xie, Danyang Zhang,  Jixuan Chen, Xiaochuan Li, Siheng Zhao, Ruisheng Cao, Toh Jing Hua, etc.
Author-email: tianbaoxiexxx@gmail.com
Classifier: Programming Language :: Python :: 3
Classifier: License :: OSI Approved :: Apache Software License
Classifier: Operating System :: OS Independent
Requires-Python: >=3.10
License-File: LICENSE
Requires-Dist: numpy<2,>=1.26
Requires-Dist: Pillow~=11.0.0
Requires-Dist: fabric
Requires-Dist: gymnasium~=0.28.1
Requires-Dist: requests
Requires-Dist: pytz~=2024.1
Requires-Dist: transformers~=4.35.2
Requires-Dist: torch~=2.5.0
Requires-Dist: opencv-python-headless<5,>=4.5
Requires-Dist: matplotlib~=3.7.4
Requires-Dist: pynput~=1.7.6
Requires-Dist: pyautogui~=0.9.54
Requires-Dist: psutil~=5.9.6
Requires-Dist: tqdm~=4.65.0
Requires-Dist: pandas<2.3,>=2.2
Requires-Dist: flask~=3.0.0
Requires-Dist: requests-toolbelt~=1.0.0
Requires-Dist: ag2~=0.9.7
Requires-Dist: lxml
Requires-Dist: cssselect
Requires-Dist: xmltodict
Requires-Dist: openpyxl
Requires-Dist: python-docx
Requires-Dist: python-pptx
Requires-Dist: pypdf
Requires-Dist: PyGetWindow
Requires-Dist: rapidfuzz
Requires-Dist: pyacoustid
Requires-Dist: pygame
Requires-Dist: ImageHash
Requires-Dist: scikit-image
Requires-Dist: librosa
Requires-Dist: pymupdf
Requires-Dist: chardet
Requires-Dist: playwright
Requires-Dist: backoff
Requires-Dist: formulas
Requires-Dist: pydrive
Requires-Dist: fastdtw
Requires-Dist: odfpy
Requires-Dist: openai
Requires-Dist: func-timeout
Requires-Dist: beautifulsoup4
Requires-Dist: dashscope
Requires-Dist: google-generativeai
Requires-Dist: PyYaml
Requires-Dist: mutagen
Requires-Dist: easyocr<2.0,>=1.6.2
Requires-Dist: borb
Requires-Dist: pypdf2
Requires-Dist: pdfplumber
Requires-Dist: wandb
Requires-Dist: wrapt_timeout_decorator
Requires-Dist: gdown
Requires-Dist: tiktoken
Requires-Dist: groq
Requires-Dist: boto3
Requires-Dist: azure-identity
Requires-Dist: azure-mgmt-compute
Requires-Dist: azure-mgmt-network
Requires-Dist: docker
Requires-Dist: loguru
Requires-Dist: dotenv
Requires-Dist: tldextract
Requires-Dist: anthropic
Requires-Dist: alibabacloud_ecs20140526
Requires-Dist: alibabacloud_tea_openapi
Requires-Dist: alibabacloud_tea_util
Dynamic: author
Dynamic: author-email
Dynamic: classifier
Dynamic: description
Dynamic: description-content-type
Dynamic: home-page
Dynamic: license-file
Dynamic: requires-dist
Dynamic: requires-python
Dynamic: summary
